logavgexp_pytorch/__init__.py
logavgexp_pytorch/logavgexp_pytorch.py
logavgexp_pytorch-0.0.7.dist-info/licenses/LICENSE
logavgexp_pytorch-0.0.7.dist-info/METADATA
logavgexp_pytorch-0.0.7.dist-info/WHEEL
logavgexp_pytorch-0.0.7.dist-info/top_level.txt
logavgexp_pytorch-0.0.7.dist-info/RECORD
