Metadata-Version: 2.4
Name: logavgexp-pytorch
Version: 0.0.7
Summary: LogAvgExp - Pytorch
Home-page: https://github.com/lucidrains/logavgexp-pytorch
Author: Phil Wang
Author-email: lucidrains@gmail.com
License: MIT
Keywords: artificial intelligence,deep learning,pytorch,logsumexp
Classifier: Development Status :: 4 - Beta
Classifier: Intended Audience :: Developers
Classifier: Topic :: Scientific/Engineering :: Artificial Intelligence
Classifier: License :: OSI Approved :: MIT License
Classifier: Programming Language :: Python :: 3.6
License-File: LICENSE
Requires-Dist: einops>=0.4.1
Requires-Dist: torch>=1.6
Requires-Dist: unfoldNd
Dynamic: author
Dynamic: author-email
Dynamic: classifier
Dynamic: home-page
Dynamic: keywords
Dynamic: license
Dynamic: license-file
Dynamic: requires-dist
Dynamic: summary
